{
    "usd": {
        "max-buy": {
            "market_name": "Капиталист №3 24/7",
            "address": "Ж/Д Вокзал, Привокзальная площадь, 1/1",
            "buy_rate": "471",
            "sell_rate": "476",
            "time": "16.07.2024, 20:51:00"
        },
        "min-buy": {
            "market_name": "Капиталист №3 24/7",
            "address": "Ж/Д Вокзал, Привокзальная площадь, 1/1",
            "buy_rate": "471",
            "sell_rate": "476",
            "time": "16.07.2024, 20:51:00"
        },
        "max-sell": {
            "market_name": "Капиталист №3 24/7",
            "address": "Ж/Д Вокзал, Привокзальная площадь, 1/1",
            "buy_rate": "471",
            "sell_rate": "476",
            "time": "16.07.2024, 20:51:00"
        },
        "min-sell": {
            "market_name": "Гермес №1",
            "address": "ул. Естая, 77, ТД \"Практик\"",
            "buy_rate": "471",
            "sell_rate": "475.5",
            "time": "16.07.2024, 17:57:30"
        }
    },
    "eur": {
        "max-buy": {
            "market_name": "Капиталист №3 24/7",
            "address": "Ж/Д Вокзал, Привокзальная площадь, 1/1",
            "buy_rate": "511",
            "sell_rate": "516",
            "time": "16.07.2024, 20:51:00"
        },
        "min-buy": {
            "market_name": "Капиталист №3 24/7",
            "address": "Ж/Д Вокзал, Привокзальная площадь, 1/1",
            "buy_rate": "511",
            "sell_rate": "516",
            "time": "16.07.2024, 20:51:00"
        },
        "max-sell": {
            "market_name": "Кайрос",
            "address": "ул. Мәшһүр Жүсіп, 16 (ТД \"Варшава\", с торца торгового дома)",
            "buy_rate": "511",
            "sell_rate": "518",
            "time": "16.07.2024, 16:56:06"
        },
        "min-sell": {
            "market_name": "Капиталист №3 24/7",
            "address": "Ж/Д Вокзал, Привокзальная площадь, 1/1",
            "buy_rate": "511",
            "sell_rate": "516",
            "time": "16.07.2024, 20:51:00"
        }
    },
    "rub": {
        "max-buy": {
            "market_name": "Кайрос",
            "address": "ул. Мәшһүр Жүсіп, 16 (ТД \"Варшава\", с торца торгового дома)",
            "buy_rate": "5.2",
            "sell_rate": "5.4",
            "time": "16.07.2024, 16:56:06"
        },
        "min-buy": {
            "market_name": "Кайрос",
            "address": "ул. Мәшһүр Жүсіп, 16 (ТД \"Варшава\", с торца торгового дома)",
            "buy_rate": "5.2",
            "sell_rate": "5.4",
            "time": "16.07.2024, 16:56:06"
        },
        "max-sell": {
            "market_name": "Кайрос",
            "address": "ул. Мәшһүр Жүсіп, 16 (ТД \"Варшава\", с торца торгового дома)",
            "buy_rate": "5.2",
            "sell_rate": "5.4",
            "time": "16.07.2024, 16:56:06"
        },
        "min-sell": {
            "market_name": "Кайрос",
            "address": "ул. Мәшһүр Жүсіп, 16 (ТД \"Варшава\", с торца торгового дома)",
            "buy_rate": "5.2",
            "sell_rate": "5.4",
            "time": "16.07.2024, 16:56:06"
        }
    },
    "kgs": {
        "max-buy": {
            "market_name": "Капиталист №3 24/7",
            "address": "Ж/Д Вокзал, Привокзальная площадь, 1/1",
            "buy_rate": "5",
            "sell_rate": "5.95",
            "time": "16.07.2024, 20:51:00"
        },
        "min-buy": {
            "market_name": "Кайрос",
            "address": "ул. Мәшһүр Жүсіп, 16 (ТД \"Варшава\", с торца торгового дома)",
            "buy_rate": "0",
            "sell_rate": "0",
            "time": "16.07.2024, 16:56:06"
        },
        "max-sell": {
            "market_name": "Капиталист №3 24/7",
            "address": "Ж/Д Вокзал, Привокзальная площадь, 1/1",
            "buy_rate": "5",
            "sell_rate": "5.95",
            "time": "16.07.2024, 20:51:00"
        },
        "min-sell": {
            "market_name": "Кайрос",
            "address": "ул. Мәшһүр Жүсіп, 16 (ТД \"Варшава\", с торца торгового дома)",
            "buy_rate": "0",
            "sell_rate": "0",
            "time": "16.07.2024, 16:56:06"
        }
    },
    "cny": {
        "max-buy": {
            "market_name": "Капиталист №3 24/7",
            "address": "Ж/Д Вокзал, Привокзальная площадь, 1/1",
            "buy_rate": "65",
            "sell_rate": "67",
            "time": "16.07.2024, 20:51:00"
        },
        "min-buy": {
            "market_name": "Капиталист №1",
            "address": "ул. Лермонтова, 82, уг. ул. М. Жусупа (бывш. ул. 1 Мая)",
            "buy_rate": "64.5",
            "sell_rate": "67",
            "time": "16.07.2024, 20:04:44"
        },
        "max-sell": {
            "market_name": "Капиталист №1",
            "address": "ул. Лермонтова, 82, уг. ул. М. Жусупа (бывш. ул. 1 Мая)",
            "buy_rate": "64.5",
            "sell_rate": "67",
            "time": "16.07.2024, 20:04:44"
        },
        "min-sell": {
            "market_name": "Капиталист №1",
            "address": "ул. Лермонтова, 82, уг. ул. М. Жусупа (бывш. ул. 1 Мая)",
            "buy_rate": "64.5",
            "sell_rate": "67",
            "time": "16.07.2024, 20:04:44"
        }
    },
    "gbp": {
        "max-buy": {
            "market_name": "Капиталист №1",
            "address": "ул. Лермонтова, 82, уг. ул. М. Жусупа (бывш. ул. 1 Мая)",
            "buy_rate": "605",
            "sell_rate": "625",
            "time": "16.07.2024, 20:04:44"
        },
        "min-buy": {
            "market_name": "Кайрос",
            "address": "ул. Мәшһүр Жүсіп, 16 (ТД \"Варшава\", с торца торгового дома)",
            "buy_rate": "0",
            "sell_rate": "0",
            "time": "16.07.2024, 16:56:06"
        },
        "max-sell": {
            "market_name": "Капиталист №1",
            "address": "ул. Лермонтова, 82, уг. ул. М. Жусупа (бывш. ул. 1 Мая)",
            "buy_rate": "605",
            "sell_rate": "625",
            "time": "16.07.2024, 20:04:44"
        },
        "min-sell": {
            "market_name": "Кайрос",
            "address": "ул. Мәшһүр Жүсіп, 16 (ТД \"Варшава\", с торца торгового дома)",
            "buy_rate": "0",
            "sell_rate": "0",
            "time": "16.07.2024, 16:56:06"
        }
    },
    "chf": {
        "max-buy": {
            "market_name": "Капиталист №1",
            "address": "ул. Лермонтова, 82, уг. ул. М. Жусупа (бывш. ул. 1 Мая)",
            "buy_rate": "0",
            "sell_rate": "0",
            "time": "16.07.2024, 20:04:44"
        },
        "min-buy": {
            "market_name": "Капиталист №1",
            "address": "ул. Лермонтова, 82, уг. ул. М. Жусупа (бывш. ул. 1 Мая)",
            "buy_rate": "0",
            "sell_rate": "0",
            "time": "16.07.2024, 20:04:44"
        },
        "max-sell": {
            "market_name": "Капиталист №1",
            "address": "ул. Лермонтова, 82, уг. ул. М. Жусупа (бывш. ул. 1 Мая)",
            "buy_rate": "0",
            "sell_rate": "0",
            "time": "16.07.2024, 20:04:44"
        },
        "min-sell": {
            "market_name": "Капиталист №1",
            "address": "ул. Лермонтова, 82, уг. ул. М. Жусупа (бывш. ул. 1 Мая)",
            "buy_rate": "0",
            "sell_rate": "0",
            "time": "16.07.2024, 20:04:44"
        }
    },
    "uzs": {
        "max-buy": {
            "market_name": "Капиталист №1",
            "address": "ул. Лермонтова, 82, уг. ул. М. Жусупа (бывш. ул. 1 Мая)",
            "buy_rate": "0.03",
            "sell_rate": "0.05",
            "time": "16.07.2024, 20:04:44"
        },
        "min-buy": {
            "market_name": "Гермес №1",
            "address": "ул. Естая, 77, ТД \"Практик\"",
            "buy_rate": "0",
            "sell_rate": "0",
            "time": "16.07.2024, 17:57:30"
        },
        "max-sell": {
            "market_name": "Капиталист №1",
            "address": "ул. Лермонтова, 82, уг. ул. М. Жусупа (бывш. ул. 1 Мая)",
            "buy_rate": "0.03",
            "sell_rate": "0.05",
            "time": "16.07.2024, 20:04:44"
        },
        "min-sell": {
            "market_name": "Гермес №1",
            "address": "ул. Естая, 77, ТД \"Практик\"",
            "buy_rate": "0",
            "sell_rate": "0",
            "time": "16.07.2024, 17:57:30"
        }
    },
    "jpy": {
        "max-buy": {
            "market_name": "Капиталист №1",
            "address": "ул. Лермонтова, 82, уг. ул. М. Жусупа (бывш. ул. 1 Мая)",
            "buy_rate": "0",
            "sell_rate": "0",
            "time": "16.07.2024, 20:04:44"
        },
        "min-buy": {
            "market_name": "Капиталист №1",
            "address": "ул. Лермонтова, 82, уг. ул. М. Жусупа (бывш. ул. 1 Мая)",
            "buy_rate": "0",
            "sell_rate": "0",
            "time": "16.07.2024, 20:04:44"
        },
        "max-sell": {
            "market_name": "Капиталист №1",
            "address": "ул. Лермонтова, 82, уг. ул. М. Жусупа (бывш. ул. 1 Мая)",
            "buy_rate": "0",
            "sell_rate": "0",
            "time": "16.07.2024, 20:04:44"
        },
        "min-sell": {
            "market_name": "Капиталист №1",
            "address": "ул. Лермонтова, 82, уг. ул. М. Жусупа (бывш. ул. 1 Мая)",
            "buy_rate": "0",
            "sell_rate": "0",
            "time": "16.07.2024, 20:04:44"
        }
    },
    "aud": {
        "max-buy": {
            "market_name": "Капиталист №1",
            "address": "ул. Лермонтова, 82, уг. ул. М. Жусупа (бывш. ул. 1 Мая)",
            "buy_rate": "0",
            "sell_rate": "0",
            "time": "16.07.2024, 20:04:44"
        },
        "min-buy": {
            "market_name": "Капиталист №1",
            "address": "ул. Лермонтова, 82, уг. ул. М. Жусупа (бывш. ул. 1 Мая)",
            "buy_rate": "0",
            "sell_rate": "0",
            "time": "16.07.2024, 20:04:44"
        },
        "max-sell": {
            "market_name": "Капиталист №1",
            "address": "ул. Лермонтова, 82, уг. ул. М. Жусупа (бывш. ул. 1 Мая)",
            "buy_rate": "0",
            "sell_rate": "0",
            "time": "16.07.2024, 20:04:44"
        },
        "min-sell": {
            "market_name": "Капиталист №1",
            "address": "ул. Лермонтова, 82, уг. ул. М. Жусупа (бывш. ул. 1 Мая)",
            "buy_rate": "0",
            "sell_rate": "0",
            "time": "16.07.2024, 20:04:44"
        }
    },
    "try": {
        "max-buy": {
            "market_name": "Капиталист №1",
            "address": "ул. Лермонтова, 82, уг. ул. М. Жусупа (бывш. ул. 1 Мая)",
            "buy_rate": "15",
            "sell_rate": "21",
            "time": "16.07.2024, 20:04:44"
        },
        "min-buy": {
            "market_name": "Гермес №1",
            "address": "ул. Естая, 77, ТД \"Практик\"",
            "buy_rate": "0",
            "sell_rate": "0",
            "time": "16.07.2024, 17:57:30"
        },
        "max-sell": {
            "market_name": "Капиталист №1",
            "address": "ул. Лермонтова, 82, уг. ул. М. Жусупа (бывш. ул. 1 Мая)",
            "buy_rate": "15",
            "sell_rate": "21",
            "time": "16.07.2024, 20:04:44"
        },
        "min-sell": {
            "market_name": "Гермес №1",
            "address": "ул. Естая, 77, ТД \"Практик\"",
            "buy_rate": "0",
            "sell_rate": "0",
            "time": "16.07.2024, 17:57:30"
        }
    },
    "aed": {
        "max-buy": {
            "market_name": "Капиталист №1",
            "address": "ул. Лермонтова, 82, уг. ул. М. Жусупа (бывш. ул. 1 Мая)",
            "buy_rate": "115",
            "sell_rate": "132",
            "time": "16.07.2024, 20:04:44"
        },
        "min-buy": {
            "market_name": "Гермес №1",
            "address": "ул. Естая, 77, ТД \"Практик\"",
            "buy_rate": "0",
            "sell_rate": "0",
            "time": "16.07.2024, 17:57:30"
        },
        "max-sell": {
            "market_name": "Капиталист №1",
            "address": "ул. Лермонтова, 82, уг. ул. М. Жусупа (бывш. ул. 1 Мая)",
            "buy_rate": "115",
            "sell_rate": "132",
            "time": "16.07.2024, 20:04:44"
        },
        "min-sell": {
            "market_name": "Гермес №1",
            "address": "ул. Естая, 77, ТД \"Практик\"",
            "buy_rate": "0",
            "sell_rate": "0",
            "time": "16.07.2024, 17:57:30"
        }
    },
    "uah": {
        "max-buy": {
            "market_name": "Капиталист №1",
            "address": "ул. Лермонтова, 82, уг. ул. М. Жусупа (бывш. ул. 1 Мая)",
            "buy_rate": "0",
            "sell_rate": "0",
            "time": "16.07.2024, 20:04:44"
        },
        "min-buy": {
            "market_name": "Капиталист №1",
            "address": "ул. Лермонтова, 82, уг. ул. М. Жусупа (бывш. ул. 1 Мая)",
            "buy_rate": "0",
            "sell_rate": "0",
            "time": "16.07.2024, 20:04:44"
        },
        "max-sell": {
            "market_name": "Капиталист №1",
            "address": "ул. Лермонтова, 82, уг. ул. М. Жусупа (бывш. ул. 1 Мая)",
            "buy_rate": "0",
            "sell_rate": "0",
            "time": "16.07.2024, 20:04:44"
        },
        "min-sell": {
            "market_name": "Капиталист №1",
            "address": "ул. Лермонтова, 82, уг. ул. М. Жусупа (бывш. ул. 1 Мая)",
            "buy_rate": "0",
            "sell_rate": "0",
            "time": "16.07.2024, 20:04:44"
        }
    },
    "thb": {
        "max-buy": {
            "market_name": "Капиталист №1",
            "address": "ул. Лермонтова, 82, уг. ул. М. Жусупа (бывш. ул. 1 Мая)",
            "buy_rate": "11",
            "sell_rate": "18",
            "time": "16.07.2024, 20:04:44"
        },
        "min-buy": {
            "market_name": "Гермес №1",
            "address": "ул. Естая, 77, ТД \"Практик\"",
            "buy_rate": "0",
            "sell_rate": "0",
            "time": "16.07.2024, 17:57:30"
        },
        "max-sell": {
            "market_name": "Капиталист №1",
            "address": "ул. Лермонтова, 82, уг. ул. М. Жусупа (бывш. ул. 1 Мая)",
            "buy_rate": "11",
            "sell_rate": "18",
            "time": "16.07.2024, 20:04:44"
        },
        "min-sell": {
            "market_name": "Гермес №1",
            "address": "ул. Естая, 77, ТД \"Практик\"",
            "buy_rate": "0",
            "sell_rate": "0",
            "time": "16.07.2024, 17:57:30"
        }
    },
    "inr": {
        "max-buy": {
            "market_name": "Капиталист №1",
            "address": "ул. Лермонтова, 82, уг. ул. М. Жусупа (бывш. ул. 1 Мая)",
            "buy_rate": "0",
            "sell_rate": "0",
            "time": "16.07.2024, 20:04:44"
        },
        "min-buy": {
            "market_name": "Капиталист №1",
            "address": "ул. Лермонтова, 82, уг. ул. М. Жусупа (бывш. ул. 1 Мая)",
            "buy_rate": "0",
            "sell_rate": "0",
            "time": "16.07.2024, 20:04:44"
        },
        "max-sell": {
            "market_name": "Капиталист №1",
            "address": "ул. Лермонтова, 82, уг. ул. М. Жусупа (бывш. ул. 1 Мая)",
            "buy_rate": "0",
            "sell_rate": "0",
            "time": "16.07.2024, 20:04:44"
        },
        "min-sell": {
            "market_name": "Капиталист №1",
            "address": "ул. Лермонтова, 82, уг. ул. М. Жусупа (бывш. ул. 1 Мая)",
            "buy_rate": "0",
            "sell_rate": "0",
            "time": "16.07.2024, 20:04:44"
        }
    },
    "egp": {
        "max-buy": {
            "market_name": "Капиталист №1",
            "address": "ул. Лермонтова, 82, уг. ул. М. Жусупа (бывш. ул. 1 Мая)",
            "buy_rate": "0",
            "sell_rate": "0",
            "time": "16.07.2024, 20:04:44"
        },
        "min-buy": {
            "market_name": "Капиталист №1",
            "address": "ул. Лермонтова, 82, уг. ул. М. Жусупа (бывш. ул. 1 Мая)",
            "buy_rate": "0",
            "sell_rate": "0",
            "time": "16.07.2024, 20:04:44"
        },
        "max-sell": {
            "market_name": "Капиталист №1",
            "address": "ул. Лермонтова, 82, уг. ул. М. Жусупа (бывш. ул. 1 Мая)",
            "buy_rate": "0",
            "sell_rate": "0",
            "time": "16.07.2024, 20:04:44"
        },
        "min-sell": {
            "market_name": "Капиталист №1",
            "address": "ул. Лермонтова, 82, уг. ул. М. Жусупа (бывш. ул. 1 Мая)",
            "buy_rate": "0",
            "sell_rate": "0",
            "time": "16.07.2024, 20:04:44"
        }
    },
    "cad": {
        "max-buy": {
            "market_name": "Капиталист №1",
            "address": "ул. Лермонтова, 82, уг. ул. М. Жусупа (бывш. ул. 1 Мая)",
            "buy_rate": "0",
            "sell_rate": "0",
            "time": "16.07.2024, 20:04:44"
        },
        "min-buy": {
            "market_name": "Капиталист №1",
            "address": "ул. Лермонтова, 82, уг. ул. М. Жусупа (бывш. ул. 1 Мая)",
            "buy_rate": "0",
            "sell_rate": "0",
            "time": "16.07.2024, 20:04:44"
        },
        "max-sell": {
            "market_name": "Капиталист №1",
            "address": "ул. Лермонтова, 82, уг. ул. М. Жусупа (бывш. ул. 1 Мая)",
            "buy_rate": "0",
            "sell_rate": "0",
            "time": "16.07.2024, 20:04:44"
        },
        "min-sell": {
            "market_name": "Капиталист №1",
            "address": "ул. Лермонтова, 82, уг. ул. М. Жусупа (бывш. ул. 1 Мая)",
            "buy_rate": "0",
            "sell_rate": "0",
            "time": "16.07.2024, 20:04:44"
        }
    },
    "kpw": {
        "max-buy": {
            "market_name": "Капиталист №1",
            "address": "ул. Лермонтова, 82, уг. ул. М. Жусупа (бывш. ул. 1 Мая)",
            "buy_rate": "0",
            "sell_rate": "0",
            "time": "16.07.2024, 20:04:44"
        },
        "min-buy": {
            "market_name": "Капиталист №1",
            "address": "ул. Лермонтова, 82, уг. ул. М. Жусупа (бывш. ул. 1 Мая)",
            "buy_rate": "0",
            "sell_rate": "0",
            "time": "16.07.2024, 20:04:44"
        },
        "max-sell": {
            "market_name": "Капиталист №1",
            "address": "ул. Лермонтова, 82, уг. ул. М. Жусупа (бывш. ул. 1 Мая)",
            "buy_rate": "0",
            "sell_rate": "0",
            "time": "16.07.2024, 20:04:44"
        },
        "min-sell": {
            "market_name": "Капиталист №1",
            "address": "ул. Лермонтова, 82, уг. ул. М. Жусупа (бывш. ул. 1 Мая)",
            "buy_rate": "0",
            "sell_rate": "0",
            "time": "16.07.2024, 20:04:44"
        }
    },
    "krw": {
        "max-buy": {
            "market_name": "Капиталист №1",
            "address": "ул. Лермонтова, 82, уг. ул. М. Жусупа (бывш. ул. 1 Мая)",
            "buy_rate": "0",
            "sell_rate": "0",
            "time": "16.07.2024, 20:04:44"
        },
        "min-buy": {
            "market_name": "Капиталист №1",
            "address": "ул. Лермонтова, 82, уг. ул. М. Жусупа (бывш. ул. 1 Мая)",
            "buy_rate": "0",
            "sell_rate": "0",
            "time": "16.07.2024, 20:04:44"
        },
        "max-sell": {
            "market_name": "Капиталист №1",
            "address": "ул. Лермонтова, 82, уг. ул. М. Жусупа (бывш. ул. 1 Мая)",
            "buy_rate": "0",
            "sell_rate": "0",
            "time": "16.07.2024, 20:04:44"
        },
        "min-sell": {
            "market_name": "Капиталист №1",
            "address": "ул. Лермонтова, 82, уг. ул. М. Жусупа (бывш. ул. 1 Мая)",
            "buy_rate": "0",
            "sell_rate": "0",
            "time": "16.07.2024, 20:04:44"
        }
    },
    "mnt": {
        "max-buy": {
            "market_name": "Капиталист №1",
            "address": "ул. Лермонтова, 82, уг. ул. М. Жусупа (бывш. ул. 1 Мая)",
            "buy_rate": "0",
            "sell_rate": "0",
            "time": "16.07.2024, 20:04:44"
        },
        "min-buy": {
            "market_name": "Капиталист №1",
            "address": "ул. Лермонтова, 82, уг. ул. М. Жусупа (бывш. ул. 1 Мая)",
            "buy_rate": "0",
            "sell_rate": "0",
            "time": "16.07.2024, 20:04:44"
        },
        "max-sell": {
            "market_name": "Капиталист №1",
            "address": "ул. Лермонтова, 82, уг. ул. М. Жусупа (бывш. ул. 1 Мая)",
            "buy_rate": "0",
            "sell_rate": "0",
            "time": "16.07.2024, 20:04:44"
        },
        "min-sell": {
            "market_name": "Капиталист №1",
            "address": "ул. Лермонтова, 82, уг. ул. М. Жусупа (бывш. ул. 1 Мая)",
            "buy_rate": "0",
            "sell_rate": "0",
            "time": "16.07.2024, 20:04:44"
        }
    },
    "tmt": {
        "max-buy": {
            "market_name": "Капиталист №1",
            "address": "ул. Лермонтова, 82, уг. ул. М. Жусупа (бывш. ул. 1 Мая)",
            "buy_rate": "0",
            "sell_rate": "0",
            "time": "16.07.2024, 20:04:44"
        },
        "min-buy": {
            "market_name": "Капиталист №1",
            "address": "ул. Лермонтова, 82, уг. ул. М. Жусупа (бывш. ул. 1 Мая)",
            "buy_rate": "0",
            "sell_rate": "0",
            "time": "16.07.2024, 20:04:44"
        },
        "max-sell": {
            "market_name": "Капиталист №1",
            "address": "ул. Лермонтова, 82, уг. ул. М. Жусупа (бывш. ул. 1 Мая)",
            "buy_rate": "0",
            "sell_rate": "0",
            "time": "16.07.2024, 20:04:44"
        },
        "min-sell": {
            "market_name": "Капиталист №1",
            "address": "ул. Лермонтова, 82, уг. ул. М. Жусупа (бывш. ул. 1 Мая)",
            "buy_rate": "0",
            "sell_rate": "0",
            "time": "16.07.2024, 20:04:44"
        }
    },
    "gel": {
        "max-buy": {
            "market_name": "Капиталист №1",
            "address": "ул. Лермонтова, 82, уг. ул. М. Жусупа (бывш. ул. 1 Мая)",
            "buy_rate": "165",
            "sell_rate": "190",
            "time": "16.07.2024, 20:04:44"
        },
        "min-buy": {
            "market_name": "Гермес №1",
            "address": "ул. Естая, 77, ТД \"Практик\"",
            "buy_rate": "0",
            "sell_rate": "0",
            "time": "16.07.2024, 17:57:30"
        },
        "max-sell": {
            "market_name": "Капиталист №1",
            "address": "ул. Лермонтова, 82, уг. ул. М. Жусупа (бывш. ул. 1 Мая)",
            "buy_rate": "165",
            "sell_rate": "190",
            "time": "16.07.2024, 20:04:44"
        },
        "min-sell": {
            "market_name": "Гермес №1",
            "address": "ул. Естая, 77, ТД \"Практик\"",
            "buy_rate": "0",
            "sell_rate": "0",
            "time": "16.07.2024, 17:57:30"
        }
    },
    "gold": {
        "max-buy": {
            "market_name": "Гермес №1",
            "address": "ул. Естая, 77, ТД \"Практик\"",
            "buy_rate": "35100",
            "sell_rate": "36500",
            "time": "16.07.2024, 17:57:30"
        },
        "min-buy": {
            "market_name": "Кайрос",
            "address": "ул. Мәшһүр Жүсіп, 16 (ТД \"Варшава\", с торца торгового дома)",
            "buy_rate": "0",
            "sell_rate": "0",
            "time": "16.07.2024, 16:56:06"
        },
        "max-sell": {
            "market_name": "РУБЛЕВЫЙ",
            "address": "ул. Лермонтова, 49",
            "buy_rate": "35000",
            "sell_rate": "37000",
            "time": "16.07.2024, 19:00:13"
        },
        "min-sell": {
            "market_name": "Кайрос",
            "address": "ул. Мәшһүр Жүсіп, 16 (ТД \"Варшава\", с торца торгового дома)",
            "buy_rate": "0",
            "sell_rate": "0",
            "time": "16.07.2024, 16:56:06"
        }
    },
    "azn": {
        "max-buy": {
            "market_name": "РУБЛЕВЫЙ",
            "address": "ул. Лермонтова, 49",
            "buy_rate": "0",
            "sell_rate": "0",
            "time": "16.07.2024, 19:00:13"
        },
        "min-buy": {
            "market_name": "РУБЛЕВЫЙ",
            "address": "ул. Лермонтова, 49",
            "buy_rate": "0",
            "sell_rate": "0",
            "time": "16.07.2024, 19:00:13"
        },
        "max-sell": {
            "market_name": "РУБЛЕВЫЙ",
            "address": "ул. Лермонтова, 49",
            "buy_rate": "0",
            "sell_rate": "0",
            "time": "16.07.2024, 19:00:13"
        },
        "min-sell": {
            "market_name": "РУБЛЕВЫЙ",
            "address": "ул. Лермонтова, 49",
            "buy_rate": "0",
            "sell_rate": "0",
            "time": "16.07.2024, 19:00:13"
        }
    },
    "bhd": {
        "max-buy": {
            "market_name": "РУБЛЕВЫЙ",
            "address": "ул. Лермонтова, 49",
            "buy_rate": "0",
            "sell_rate": "0",
            "time": "16.07.2024, 19:00:13"
        },
        "min-buy": {
            "market_name": "РУБЛЕВЫЙ",
            "address": "ул. Лермонтова, 49",
            "buy_rate": "0",
            "sell_rate": "0",
            "time": "16.07.2024, 19:00:13"
        },
        "max-sell": {
            "market_name": "РУБЛЕВЫЙ",
            "address": "ул. Лермонтова, 49",
            "buy_rate": "0",
            "sell_rate": "0",
            "time": "16.07.2024, 19:00:13"
        },
        "min-sell": {
            "market_name": "РУБЛЕВЫЙ",
            "address": "ул. Лермонтова, 49",
            "buy_rate": "0",
            "sell_rate": "0",
            "time": "16.07.2024, 19:00:13"
        }
    },
    "amd": {
        "max-buy": {
            "market_name": "РУБЛЕВЫЙ",
            "address": "ул. Лермонтова, 49",
            "buy_rate": "0",
            "sell_rate": "0",
            "time": "16.07.2024, 19:00:13"
        },
        "min-buy": {
            "market_name": "РУБЛЕВЫЙ",
            "address": "ул. Лермонтова, 49",
            "buy_rate": "0",
            "sell_rate": "0",
            "time": "16.07.2024, 19:00:13"
        },
        "max-sell": {
            "market_name": "РУБЛЕВЫЙ",
            "address": "ул. Лермонтова, 49",
            "buy_rate": "0",
            "sell_rate": "0",
            "time": "16.07.2024, 19:00:13"
        },
        "min-sell": {
            "market_name": "РУБЛЕВЫЙ",
            "address": "ул. Лермонтова, 49",
            "buy_rate": "0",
            "sell_rate": "0",
            "time": "16.07.2024, 19:00:13"
        }
    },
    "byn": {
        "max-buy": {
            "market_name": "РУБЛЕВЫЙ",
            "address": "ул. Лермонтова, 49",
            "buy_rate": "0",
            "sell_rate": "0",
            "time": "16.07.2024, 19:00:13"
        },
        "min-buy": {
            "market_name": "РУБЛЕВЫЙ",
            "address": "ул. Лермонтова, 49",
            "buy_rate": "0",
            "sell_rate": "0",
            "time": "16.07.2024, 19:00:13"
        },
        "max-sell": {
            "market_name": "РУБЛЕВЫЙ",
            "address": "ул. Лермонтова, 49",
            "buy_rate": "0",
            "sell_rate": "0",
            "time": "16.07.2024, 19:00:13"
        },
        "min-sell": {
            "market_name": "РУБЛЕВЫЙ",
            "address": "ул. Лермонтова, 49",
            "buy_rate": "0",
            "sell_rate": "0",
            "time": "16.07.2024, 19:00:13"
        }
    },
    "brl": {
        "max-buy": {
            "market_name": "РУБЛЕВЫЙ",
            "address": "ул. Лермонтова, 49",
            "buy_rate": "0",
            "sell_rate": "0",
            "time": "16.07.2024, 19:00:13"
        },
        "min-buy": {
            "market_name": "РУБЛЕВЫЙ",
            "address": "ул. Лермонтова, 49",
            "buy_rate": "0",
            "sell_rate": "0",
            "time": "16.07.2024, 19:00:13"
        },
        "max-sell": {
            "market_name": "РУБЛЕВЫЙ",
            "address": "ул. Лермонтова, 49",
            "buy_rate": "0",
            "sell_rate": "0",
            "time": "16.07.2024, 19:00:13"
        },
        "min-sell": {
            "market_name": "РУБЛЕВЫЙ",
            "address": "ул. Лермонтова, 49",
            "buy_rate": "0",
            "sell_rate": "0",
            "time": "16.07.2024, 19:00:13"
        }
    },
    "huf": {
        "max-buy": {
            "market_name": "РУБЛЕВЫЙ",
            "address": "ул. Лермонтова, 49",
            "buy_rate": "0",
            "sell_rate": "0",
            "time": "16.07.2024, 19:00:13"
        },
        "min-buy": {
            "market_name": "РУБЛЕВЫЙ",
            "address": "ул. Лермонтова, 49",
            "buy_rate": "0",
            "sell_rate": "0",
            "time": "16.07.2024, 19:00:13"
        },
        "max-sell": {
            "market_name": "РУБЛЕВЫЙ",
            "address": "ул. Лермонтова, 49",
            "buy_rate": "0",
            "sell_rate": "0",
            "time": "16.07.2024, 19:00:13"
        },
        "min-sell": {
            "market_name": "РУБЛЕВЫЙ",
            "address": "ул. Лермонтова, 49",
            "buy_rate": "0",
            "sell_rate": "0",
            "time": "16.07.2024, 19:00:13"
        }
    },
    "hkd": {
        "max-buy": {
            "market_name": "РУБЛЕВЫЙ",
            "address": "ул. Лермонтова, 49",
            "buy_rate": "0",
            "sell_rate": "0",
            "time": "16.07.2024, 19:00:13"
        },
        "min-buy": {
            "market_name": "РУБЛЕВЫЙ",
            "address": "ул. Лермонтова, 49",
            "buy_rate": "0",
            "sell_rate": "0",
            "time": "16.07.2024, 19:00:13"
        },
        "max-sell": {
            "market_name": "РУБЛЕВЫЙ",
            "address": "ул. Лермонтова, 49",
            "buy_rate": "0",
            "sell_rate": "0",
            "time": "16.07.2024, 19:00:13"
        },
        "min-sell": {
            "market_name": "РУБЛЕВЫЙ",
            "address": "ул. Лермонтова, 49",
            "buy_rate": "0",
            "sell_rate": "0",
            "time": "16.07.2024, 19:00:13"
        }
    },
    "dkk": {
        "max-buy": {
            "market_name": "РУБЛЕВЫЙ",
            "address": "ул. Лермонтова, 49",
            "buy_rate": "0",
            "sell_rate": "0",
            "time": "16.07.2024, 19:00:13"
        },
        "min-buy": {
            "market_name": "РУБЛЕВЫЙ",
            "address": "ул. Лермонтова, 49",
            "buy_rate": "0",
            "sell_rate": "0",
            "time": "16.07.2024, 19:00:13"
        },
        "max-sell": {
            "market_name": "РУБЛЕВЫЙ",
            "address": "ул. Лермонтова, 49",
            "buy_rate": "0",
            "sell_rate": "0",
            "time": "16.07.2024, 19:00:13"
        },
        "min-sell": {
            "market_name": "РУБЛЕВЫЙ",
            "address": "ул. Лермонтова, 49",
            "buy_rate": "0",
            "sell_rate": "0",
            "time": "16.07.2024, 19:00:13"
        }
    },
    "irr": {
        "max-buy": {
            "market_name": "РУБЛЕВЫЙ",
            "address": "ул. Лермонтова, 49",
            "buy_rate": "0",
            "sell_rate": "0",
            "time": "16.07.2024, 19:00:13"
        },
        "min-buy": {
            "market_name": "РУБЛЕВЫЙ",
            "address": "ул. Лермонтова, 49",
            "buy_rate": "0",
            "sell_rate": "0",
            "time": "16.07.2024, 19:00:13"
        },
        "max-sell": {
            "market_name": "РУБЛЕВЫЙ",
            "address": "ул. Лермонтова, 49",
            "buy_rate": "0",
            "sell_rate": "0",
            "time": "16.07.2024, 19:00:13"
        },
        "min-sell": {
            "market_name": "РУБЛЕВЫЙ",
            "address": "ул. Лермонтова, 49",
            "buy_rate": "0",
            "sell_rate": "0",
            "time": "16.07.2024, 19:00:13"
        }
    },
    "kwd": {
        "max-buy": {
            "market_name": "РУБЛЕВЫЙ",
            "address": "ул. Лермонтова, 49",
            "buy_rate": "0",
            "sell_rate": "0",
            "time": "16.07.2024, 19:00:13"
        },
        "min-buy": {
            "market_name": "РУБЛЕВЫЙ",
            "address": "ул. Лермонтова, 49",
            "buy_rate": "0",
            "sell_rate": "0",
            "time": "16.07.2024, 19:00:13"
        },
        "max-sell": {
            "market_name": "РУБЛЕВЫЙ",
            "address": "ул. Лермонтова, 49",
            "buy_rate": "0",
            "sell_rate": "0",
            "time": "16.07.2024, 19:00:13"
        },
        "min-sell": {
            "market_name": "РУБЛЕВЫЙ",
            "address": "ул. Лермонтова, 49",
            "buy_rate": "0",
            "sell_rate": "0",
            "time": "16.07.2024, 19:00:13"
        }
    },
    "myr": {
        "max-buy": {
            "market_name": "РУБЛЕВЫЙ",
            "address": "ул. Лермонтова, 49",
            "buy_rate": "0",
            "sell_rate": "0",
            "time": "16.07.2024, 19:00:13"
        },
        "min-buy": {
            "market_name": "РУБЛЕВЫЙ",
            "address": "ул. Лермонтова, 49",
            "buy_rate": "0",
            "sell_rate": "0",
            "time": "16.07.2024, 19:00:13"
        },
        "max-sell": {
            "market_name": "РУБЛЕВЫЙ",
            "address": "ул. Лермонтова, 49",
            "buy_rate": "0",
            "sell_rate": "0",
            "time": "16.07.2024, 19:00:13"
        },
        "min-sell": {
            "market_name": "РУБЛЕВЫЙ",
            "address": "ул. Лермонтова, 49",
            "buy_rate": "0",
            "sell_rate": "0",
            "time": "16.07.2024, 19:00:13"
        }
    },
    "mxn": {
        "max-buy": {
            "market_name": "РУБЛЕВЫЙ",
            "address": "ул. Лермонтова, 49",
            "buy_rate": "0",
            "sell_rate": "0",
            "time": "16.07.2024, 19:00:13"
        },
        "min-buy": {
            "market_name": "РУБЛЕВЫЙ",
            "address": "ул. Лермонтова, 49",
            "buy_rate": "0",
            "sell_rate": "0",
            "time": "16.07.2024, 19:00:13"
        },
        "max-sell": {
            "market_name": "РУБЛЕВЫЙ",
            "address": "ул. Лермонтова, 49",
            "buy_rate": "0",
            "sell_rate": "0",
            "time": "16.07.2024, 19:00:13"
        },
        "min-sell": {
            "market_name": "РУБЛЕВЫЙ",
            "address": "ул. Лермонтова, 49",
            "buy_rate": "0",
            "sell_rate": "0",
            "time": "16.07.2024, 19:00:13"
        }
    },
    "mdl": {
        "max-buy": {
            "market_name": "РУБЛЕВЫЙ",
            "address": "ул. Лермонтова, 49",
            "buy_rate": "0",
            "sell_rate": "0",
            "time": "16.07.2024, 19:00:13"
        },
        "min-buy": {
            "market_name": "РУБЛЕВЫЙ",
            "address": "ул. Лермонтова, 49",
            "buy_rate": "0",
            "sell_rate": "0",
            "time": "16.07.2024, 19:00:13"
        },
        "max-sell": {
            "market_name": "РУБЛЕВЫЙ",
            "address": "ул. Лермонтова, 49",
            "buy_rate": "0",
            "sell_rate": "0",
            "time": "16.07.2024, 19:00:13"
        },
        "min-sell": {
            "market_name": "РУБЛЕВЫЙ",
            "address": "ул. Лермонтова, 49",
            "buy_rate": "0",
            "sell_rate": "0",
            "time": "16.07.2024, 19:00:13"
        }
    },
    "nok": {
        "max-buy": {
            "market_name": "РУБЛЕВЫЙ",
            "address": "ул. Лермонтова, 49",
            "buy_rate": "0",
            "sell_rate": "0",
            "time": "16.07.2024, 19:00:13"
        },
        "min-buy": {
            "market_name": "РУБЛЕВЫЙ",
            "address": "ул. Лермонтова, 49",
            "buy_rate": "0",
            "sell_rate": "0",
            "time": "16.07.2024, 19:00:13"
        },
        "max-sell": {
            "market_name": "РУБЛЕВЫЙ",
            "address": "ул. Лермонтова, 49",
            "buy_rate": "0",
            "sell_rate": "0",
            "time": "16.07.2024, 19:00:13"
        },
        "min-sell": {
            "market_name": "РУБЛЕВЫЙ",
            "address": "ул. Лермонтова, 49",
            "buy_rate": "0",
            "sell_rate": "0",
            "time": "16.07.2024, 19:00:13"
        }
    },
    "pln": {
        "max-buy": {
            "market_name": "РУБЛЕВЫЙ",
            "address": "ул. Лермонтова, 49",
            "buy_rate": "0",
            "sell_rate": "0",
            "time": "16.07.2024, 19:00:13"
        },
        "min-buy": {
            "market_name": "РУБЛЕВЫЙ",
            "address": "ул. Лермонтова, 49",
            "buy_rate": "0",
            "sell_rate": "0",
            "time": "16.07.2024, 19:00:13"
        },
        "max-sell": {
            "market_name": "РУБЛЕВЫЙ",
            "address": "ул. Лермонтова, 49",
            "buy_rate": "0",
            "sell_rate": "0",
            "time": "16.07.2024, 19:00:13"
        },
        "min-sell": {
            "market_name": "РУБЛЕВЫЙ",
            "address": "ул. Лермонтова, 49",
            "buy_rate": "0",
            "sell_rate": "0",
            "time": "16.07.2024, 19:00:13"
        }
    },
    "sar": {
        "max-buy": {
            "market_name": "РУБЛЕВЫЙ",
            "address": "ул. Лермонтова, 49",
            "buy_rate": "0",
            "sell_rate": "0",
            "time": "16.07.2024, 19:00:13"
        },
        "min-buy": {
            "market_name": "РУБЛЕВЫЙ",
            "address": "ул. Лермонтова, 49",
            "buy_rate": "0",
            "sell_rate": "0",
            "time": "16.07.2024, 19:00:13"
        },
        "max-sell": {
            "market_name": "РУБЛЕВЫЙ",
            "address": "ул. Лермонтова, 49",
            "buy_rate": "0",
            "sell_rate": "0",
            "time": "16.07.2024, 19:00:13"
        },
        "min-sell": {
            "market_name": "РУБЛЕВЫЙ",
            "address": "ул. Лермонтова, 49",
            "buy_rate": "0",
            "sell_rate": "0",
            "time": "16.07.2024, 19:00:13"
        }
    },
    "xdr": {
        "max-buy": {
            "market_name": "РУБЛЕВЫЙ",
            "address": "ул. Лермонтова, 49",
            "buy_rate": "0",
            "sell_rate": "0",
            "time": "16.07.2024, 19:00:13"
        },
        "min-buy": {
            "market_name": "РУБЛЕВЫЙ",
            "address": "ул. Лермонтова, 49",
            "buy_rate": "0",
            "sell_rate": "0",
            "time": "16.07.2024, 19:00:13"
        },
        "max-sell": {
            "market_name": "РУБЛЕВЫЙ",
            "address": "ул. Лермонтова, 49",
            "buy_rate": "0",
            "sell_rate": "0",
            "time": "16.07.2024, 19:00:13"
        },
        "min-sell": {
            "market_name": "РУБЛЕВЫЙ",
            "address": "ул. Лермонтова, 49",
            "buy_rate": "0",
            "sell_rate": "0",
            "time": "16.07.2024, 19:00:13"
        }
    },
    "sgd": {
        "max-buy": {
            "market_name": "РУБЛЕВЫЙ",
            "address": "ул. Лермонтова, 49",
            "buy_rate": "0",
            "sell_rate": "0",
            "time": "16.07.2024, 19:00:13"
        },
        "min-buy": {
            "market_name": "РУБЛЕВЫЙ",
            "address": "ул. Лермонтова, 49",
            "buy_rate": "0",
            "sell_rate": "0",
            "time": "16.07.2024, 19:00:13"
        },
        "max-sell": {
            "market_name": "РУБЛЕВЫЙ",
            "address": "ул. Лермонтова, 49",
            "buy_rate": "0",
            "sell_rate": "0",
            "time": "16.07.2024, 19:00:13"
        },
        "min-sell": {
            "market_name": "РУБЛЕВЫЙ",
            "address": "ул. Лермонтова, 49",
            "buy_rate": "0",
            "sell_rate": "0",
            "time": "16.07.2024, 19:00:13"
        }
    },
    "tjs": {
        "max-buy": {
            "market_name": "РУБЛЕВЫЙ",
            "address": "ул. Лермонтова, 49",
            "buy_rate": "0",
            "sell_rate": "0",
            "time": "16.07.2024, 19:00:13"
        },
        "min-buy": {
            "market_name": "РУБЛЕВЫЙ",
            "address": "ул. Лермонтова, 49",
            "buy_rate": "0",
            "sell_rate": "0",
            "time": "16.07.2024, 19:00:13"
        },
        "max-sell": {
            "market_name": "РУБЛЕВЫЙ",
            "address": "ул. Лермонтова, 49",
            "buy_rate": "0",
            "sell_rate": "0",
            "time": "16.07.2024, 19:00:13"
        },
        "min-sell": {
            "market_name": "РУБЛЕВЫЙ",
            "address": "ул. Лермонтова, 49",
            "buy_rate": "0",
            "sell_rate": "0",
            "time": "16.07.2024, 19:00:13"
        }
    },
    "czk": {
        "max-buy": {
            "market_name": "РУБЛЕВЫЙ",
            "address": "ул. Лермонтова, 49",
            "buy_rate": "0",
            "sell_rate": "0",
            "time": "16.07.2024, 19:00:13"
        },
        "min-buy": {
            "market_name": "РУБЛЕВЫЙ",
            "address": "ул. Лермонтова, 49",
            "buy_rate": "0",
            "sell_rate": "0",
            "time": "16.07.2024, 19:00:13"
        },
        "max-sell": {
            "market_name": "РУБЛЕВЫЙ",
            "address": "ул. Лермонтова, 49",
            "buy_rate": "0",
            "sell_rate": "0",
            "time": "16.07.2024, 19:00:13"
        },
        "min-sell": {
            "market_name": "РУБЛЕВЫЙ",
            "address": "ул. Лермонтова, 49",
            "buy_rate": "0",
            "sell_rate": "0",
            "time": "16.07.2024, 19:00:13"
        }
    },
    "sek": {
        "max-buy": {
            "market_name": "РУБЛЕВЫЙ",
            "address": "ул. Лермонтова, 49",
            "buy_rate": "0",
            "sell_rate": "0",
            "time": "16.07.2024, 19:00:13"
        },
        "min-buy": {
            "market_name": "РУБЛЕВЫЙ",
            "address": "ул. Лермонтова, 49",
            "buy_rate": "0",
            "sell_rate": "0",
            "time": "16.07.2024, 19:00:13"
        },
        "max-sell": {
            "market_name": "РУБЛЕВЫЙ",
            "address": "ул. Лермонтова, 49",
            "buy_rate": "0",
            "sell_rate": "0",
            "time": "16.07.2024, 19:00:13"
        },
        "min-sell": {
            "market_name": "РУБЛЕВЫЙ",
            "address": "ул. Лермонтова, 49",
            "buy_rate": "0",
            "sell_rate": "0",
            "time": "16.07.2024, 19:00:13"
        }
    },
    "zar": {
        "max-buy": {
            "market_name": "РУБЛЕВЫЙ",
            "address": "ул. Лермонтова, 49",
            "buy_rate": "0",
            "sell_rate": "0",
            "time": "16.07.2024, 19:00:13"
        },
        "min-buy": {
            "market_name": "РУБЛЕВЫЙ",
            "address": "ул. Лермонтова, 49",
            "buy_rate": "0",
            "sell_rate": "0",
            "time": "16.07.2024, 19:00:13"
        },
        "max-sell": {
            "market_name": "РУБЛЕВЫЙ",
            "address": "ул. Лермонтова, 49",
            "buy_rate": "0",
            "sell_rate": "0",
            "time": "16.07.2024, 19:00:13"
        },
        "min-sell": {
            "market_name": "РУБЛЕВЫЙ",
            "address": "ул. Лермонтова, 49",
            "buy_rate": "0",
            "sell_rate": "0",
            "time": "16.07.2024, 19:00:13"
        }
    },
    "ils": {
        "max-buy": {
            "market_name": "РУБЛЕВЫЙ",
            "address": "ул. Лермонтова, 49",
            "buy_rate": "0",
            "sell_rate": "0",
            "time": "16.07.2024, 19:00:13"
        },
        "min-buy": {
            "market_name": "РУБЛЕВЫЙ",
            "address": "ул. Лермонтова, 49",
            "buy_rate": "0",
            "sell_rate": "0",
            "time": "16.07.2024, 19:00:13"
        },
        "max-sell": {
            "market_name": "РУБЛЕВЫЙ",
            "address": "ул. Лермонтова, 49",
            "buy_rate": "0",
            "sell_rate": "0",
            "time": "16.07.2024, 19:00:13"
        },
        "min-sell": {
            "market_name": "РУБЛЕВЫЙ",
            "address": "ул. Лермонтова, 49",
            "buy_rate": "0",
            "sell_rate": "0",
            "time": "16.07.2024, 19:00:13"
        }
    },
    "qar": {
        "max-buy": {
            "market_name": "РУБЛЕВЫЙ",
            "address": "ул. Лермонтова, 49",
            "buy_rate": "0",
            "sell_rate": "0",
            "time": "16.07.2024, 19:00:13"
        },
        "min-buy": {
            "market_name": "РУБЛЕВЫЙ",
            "address": "ул. Лермонтова, 49",
            "buy_rate": "0",
            "sell_rate": "0",
            "time": "16.07.2024, 19:00:13"
        },
        "max-sell": {
            "market_name": "РУБЛЕВЫЙ",
            "address": "ул. Лермонтова, 49",
            "buy_rate": "0",
            "sell_rate": "0",
            "time": "16.07.2024, 19:00:13"
        },
        "min-sell": {
            "market_name": "РУБЛЕВЫЙ",
            "address": "ул. Лермонтова, 49",
            "buy_rate": "0",
            "sell_rate": "0",
            "time": "16.07.2024, 19:00:13"
        }
    },
    "vnd": {
        "max-buy": {
            "market_name": "РУБЛЕВЫЙ",
            "address": "ул. Лермонтова, 49",
            "buy_rate": "0",
            "sell_rate": "0",
            "time": "16.07.2024, 19:00:13"
        },
        "min-buy": {
            "market_name": "РУБЛЕВЫЙ",
            "address": "ул. Лермонтова, 49",
            "buy_rate": "0",
            "sell_rate": "0",
            "time": "16.07.2024, 19:00:13"
        },
        "max-sell": {
            "market_name": "РУБЛЕВЫЙ",
            "address": "ул. Лермонтова, 49",
            "buy_rate": "0",
            "sell_rate": "0",
            "time": "16.07.2024, 19:00:13"
        },
        "min-sell": {
            "market_name": "РУБЛЕВЫЙ",
            "address": "ул. Лермонтова, 49",
            "buy_rate": "0",
            "sell_rate": "0",
            "time": "16.07.2024, 19:00:13"
        }
    },
    "lkr": {
        "max-buy": {
            "market_name": "РУБЛЕВЫЙ",
            "address": "ул. Лермонтова, 49",
            "buy_rate": "0",
            "sell_rate": "0",
            "time": "16.07.2024, 19:00:13"
        },
        "min-buy": {
            "market_name": "РУБЛЕВЫЙ",
            "address": "ул. Лермонтова, 49",
            "buy_rate": "0",
            "sell_rate": "0",
            "time": "16.07.2024, 19:00:13"
        },
        "max-sell": {
            "market_name": "РУБЛЕВЫЙ",
            "address": "ул. Лермонтова, 49",
            "buy_rate": "0",
            "sell_rate": "0",
            "time": "16.07.2024, 19:00:13"
        },
        "min-sell": {
            "market_name": "РУБЛЕВЫЙ",
            "address": "ул. Лермонтова, 49",
            "buy_rate": "0",
            "sell_rate": "0",
            "time": "16.07.2024, 19:00:13"
        }
    },
    "omr": {
        "max-buy": {
            "market_name": "РУБЛЕВЫЙ",
            "address": "ул. Лермонтова, 49",
            "buy_rate": "0",
            "sell_rate": "0",
            "time": "16.07.2024, 19:00:13"
        },
        "min-buy": {
            "market_name": "РУБЛЕВЫЙ",
            "address": "ул. Лермонтова, 49",
            "buy_rate": "0",
            "sell_rate": "0",
            "time": "16.07.2024, 19:00:13"
        },
        "max-sell": {
            "market_name": "РУБЛЕВЫЙ",
            "address": "ул. Лермонтова, 49",
            "buy_rate": "0",
            "sell_rate": "0",
            "time": "16.07.2024, 19:00:13"
        },
        "min-sell": {
            "market_name": "РУБЛЕВЫЙ",
            "address": "ул. Лермонтова, 49",
            "buy_rate": "0",
            "sell_rate": "0",
            "time": "16.07.2024, 19:00:13"
        }
    },
    "pkr": {
        "max-buy": {
            "market_name": "РУБЛЕВЫЙ",
            "address": "ул. Лермонтова, 49",
            "buy_rate": "0",
            "sell_rate": "0",
            "time": "16.07.2024, 19:00:13"
        },
        "min-buy": {
            "market_name": "РУБЛЕВЫЙ",
            "address": "ул. Лермонтова, 49",
            "buy_rate": "0",
            "sell_rate": "0",
            "time": "16.07.2024, 19:00:13"
        },
        "max-sell": {
            "market_name": "РУБЛЕВЫЙ",
            "address": "ул. Лермонтова, 49",
            "buy_rate": "0",
            "sell_rate": "0",
            "time": "16.07.2024, 19:00:13"
        },
        "min-sell": {
            "market_name": "РУБЛЕВЫЙ",
            "address": "ул. Лермонтова, 49",
            "buy_rate": "0",
            "sell_rate": "0",
            "time": "16.07.2024, 19:00:13"
        }
    },
    "mvr": {
        "max-buy": {
            "market_name": "РУБЛЕВЫЙ",
            "address": "ул. Лермонтова, 49",
            "buy_rate": "0",
            "sell_rate": "0",
            "time": "16.07.2024, 19:00:13"
        },
        "min-buy": {
            "market_name": "РУБЛЕВЫЙ",
            "address": "ул. Лермонтова, 49",
            "buy_rate": "0",
            "sell_rate": "0",
            "time": "16.07.2024, 19:00:13"
        },
        "max-sell": {
            "market_name": "РУБЛЕВЫЙ",
            "address": "ул. Лермонтова, 49",
            "buy_rate": "0",
            "sell_rate": "0",
            "time": "16.07.2024, 19:00:13"
        },
        "min-sell": {
            "market_name": "РУБЛЕВЫЙ",
            "address": "ул. Лермонтова, 49",
            "buy_rate": "0",
            "sell_rate": "0",
            "time": "16.07.2024, 19:00:13"
        }
    },
    "idr": {
        "max-buy": {
            "market_name": "РУБЛЕВЫЙ",
            "address": "ул. Лермонтова, 49",
            "buy_rate": "0",
            "sell_rate": "0",
            "time": "16.07.2024, 19:00:13"
        },
        "min-buy": {
            "market_name": "РУБЛЕВЫЙ",
            "address": "ул. Лермонтова, 49",
            "buy_rate": "0",
            "sell_rate": "0",
            "time": "16.07.2024, 19:00:13"
        },
        "max-sell": {
            "market_name": "РУБЛЕВЫЙ",
            "address": "ул. Лермонтова, 49",
            "buy_rate": "0",
            "sell_rate": "0",
            "time": "16.07.2024, 19:00:13"
        },
        "min-sell": {
            "market_name": "РУБЛЕВЫЙ",
            "address": "ул. Лермонтова, 49",
            "buy_rate": "0",
            "sell_rate": "0",
            "time": "16.07.2024, 19:00:13"
        }
    }
}